DAPyr/DA.py
DAPyr/Exceptions.py
DAPyr/INFLATION.py
DAPyr/MISC.py
DAPyr/MODELS.py
DAPyr/OBS_ERRORS.py
DAPyr/__init__.py
dapyr-1.0.0.dist-info/METADATA
dapyr-1.0.0.dist-info/WHEEL
dapyr-1.0.0.dist-info/RECORD
