Metadata-Version: 2.4
Name: DAPyr
Version: 1.0.0
Summary: A Python package for running idealized model data assimilation experiments
Project-URL: Homepage, https://github.com/nikolaitM/DApyr
Project-URL: Documentation, https://dapyr.readthedocs.io/en/latest/
Project-URL: Issues, https://github.com/nikolaitM/DApyr/issues
Author-email: Maria Nikolaitchik <mnikolai@umd.edu>
License: MIT
Keywords: DA,Lorenz,data assimilation
Classifier: Operating System :: OS Independent
Classifier: Programming Language :: Python :: 3
Requires-Python: >=3.10
Requires-Dist: matplotlib>=3.10.0
Requires-Dist: numba>=0.60.0
Requires-Dist: numbalsoda>=0.3.4
Requires-Dist: numpy>=1.26.1
Requires-Dist: scipy>=1.15.2
Requires-Dist: xarray>=2024.11.0
